odoo/addons/shopinvader_customer_multi_user/README.rst
odoo/addons/shopinvader_customer_multi_user/__init__.py
odoo/addons/shopinvader_customer_multi_user/__manifest__.py
odoo/addons/shopinvader_customer_multi_user/components/__init__.py
odoo/addons/shopinvader_customer_multi_user/components/access_info.py
odoo/addons/shopinvader_customer_multi_user/i18n/shopinvader_customer_multi_user.pot
odoo/addons/shopinvader_customer_multi_user/migrations/13.0.1.1.0/pre-migrate.py
odoo/addons/shopinvader_customer_multi_user/migrations/13.0.1.2.0/post-migrate.py
odoo/addons/shopinvader_customer_multi_user/models/__init__.py
odoo/addons/shopinvader_customer_multi_user/models/res_partner.py
odoo/addons/shopinvader_customer_multi_user/models/shopinvader_backend.py
odoo/addons/shopinvader_customer_multi_user/models/shopinvader_partner.py
odoo/addons/shopinvader_customer_multi_user/readme/CONTRIBUTORS.rst
odoo/addons/shopinvader_customer_multi_user/readme/CREDITS.rst
odoo/addons/shopinvader_customer_multi_user/readme/DESCRIPTION.rst
odoo/addons/shopinvader_customer_multi_user/readme/USAGE.rst
odoo/addons/shopinvader_customer_multi_user/services/__init__.py
odoo/addons/shopinvader_customer_multi_user/services/address.py
odoo/addons/shopinvader_customer_multi_user/services/customer.py
odoo/addons/shopinvader_customer_multi_user/services/service.py
odoo/addons/shopinvader_customer_multi_user/services/user_management.py
odoo/addons/shopinvader_customer_multi_user/static/description/index.html
odoo/addons/shopinvader_customer_multi_user/tests/__init__.py
odoo/addons/shopinvader_customer_multi_user/tests/common.py
odoo/addons/shopinvader_customer_multi_user/tests/test_multi_user_customer.py
odoo/addons/shopinvader_customer_multi_user/tests/test_multi_user_management.py
odoo/addons/shopinvader_customer_multi_user/tests/test_multi_user_partner.py
odoo/addons/shopinvader_customer_multi_user/tests/test_multi_user_service_ctx.py
odoo13_addon_shopinvader_customer_multi_user-13.0.2.3.0.dist-info/METADATA
odoo13_addon_shopinvader_customer_multi_user-13.0.2.3.0.dist-info/WHEEL
odoo13_addon_shopinvader_customer_multi_user-13.0.2.3.0.dist-info/top_level.txt
odoo13_addon_shopinvader_customer_multi_user-13.0.2.3.0.dist-info/RECORD
