Metadata-Version: 2.1
Name: odoo13-addon-shopinvader-customer-multi-user
Version: 13.0.2.3.0
Summary: Enable registration of multiple users per each company customer.
Home-page: https://github.com/shopinvader/odoo-shopinvader
Author: Camptocamp SA
License: AGPL-3
Platform: UNKNOWN
Classifier: Programming Language :: Python
Classifier: Framework :: Odoo
Classifier: Framework :: Odoo :: 13.0
Classifier: License :: OSI Approved :: GNU Affero General Public License v3
Requires-Python: >=3.5
Requires-Dist: odoo13-addon-shopinvader
Requires-Dist: odoo (<13.1dev,>=13.0a)
